
{
  "North-East": {
        "Tizi Ouzou": ["Tizi Ouzou Centre", "Aïn El Hammam", "Azazga"],
        "Algiers": ["Algiers Centre", "Bab El Oued", "Kouba"],
        "Médéa": ["Médéa Centre", "Ouled Bouachra", "Tizi Mahdi"],
        "El Tarf": ["El Tarf Centre", "Bouteldja", "Aïn El Assel"],
        "Tébessa": ["Tébessa Centre", "El Ogla", "Bir El Ater"],
        "Constantine": ["Constantine Centre", "Ibn Ziad", "El Khroub"],
        "Skikda": ["Skikda Centre", "Aïn Zouit", "Oued Zhour"],
        "Sétif": ["Sétif Centre", "Bir El Kebir", "Aïn Abessa"],
        "Jijel": ["Jijel Centre", "El Aouana", "Kaous"],
        "Béjaïa": ["Béjaïa Centre", "Tichy", "Amizour"]
      },
      "North-West": {
        "Mostaganem": ["Mostaganem Centre", "Achaacha", "Hadjadj"],
        "Mascara": ["Mascara Centre", "El Ghomri", "Tizi"],
        "Oran": ["Oran Centre", "Bir El Djir", "Es Senia"],
        "El Bayadh": ["El Bayadh Centre", "Boualem", "Brezina"],
        "Relizane": ["Relizane Centre", "Mazouna", "Oued Rhiou"],
        "Chlef": ["Chlef Centre", "El Karimia", "Ténès"],
        "Tlemcen": ["Tlemcen Centre", "Maghnia", "Beni Snous"],
        "Saïda": ["Saïda Centre", "Aïn Soltane", "Doui Thabet"],
        "Tiaret": ["Tiaret Centre", "Aïn Deheb", "Mechraa Sfa"],
        "Aïn Témouchent": ["Aïn Témouchent Centre", "Aïn Kihal", "El Malah"]
      },
    "South": {
      "Béchar": ["Béchar Centre", "Béni Abbès", "Mogheul"],
      "Tindouf": ["Tindouf Centre", "Oum El Assel", "Béchar El Oued"],
      "El Oued": ["El Oued Centre", "Guemar", "El M'Ghair"],
      "Khenchela": ["Khenchela Centre", "Babar", "El Hamma"],
      "Souk Ahras": ["Souk Ahras Centre", "M'Sila El Hadjadj", "Taoura"],
      "Tipaza": ["Tipaza Centre", "Hadjout", "Gouraya"],
      "Mila": ["Mila Centre", "Tassadane Haddada", "Grarem Gouga"],
      "Ghardaïa": ["Ghardaïa Centre", "Metlili", "El Guerrara"],
      "Laghouat": ["Laghouat Centre", "Ksar El Hirane", "Bordj Belounis"],
      "Ouargla": ["Ouargla Centre", "Aïn El Beida", "N'Goussa"]
    }
}
  